protograf/__init__.py
protograf/_version.py
protograf/base.py
protograf/base_extended.py
protograf/bgg.py
protograf/defaults.json
protograf/dice.py
protograf/globals.py
protograf/groups.py
protograf/layouts.py
protograf/objects.py
protograf/proto.py
protograf/scripts/__init__.py
protograf/scripts/counter_extraction.py
protograf/scripts/sample.ini
protograf/scripts/utils.py
protograf/shapes.py
protograf/shapes_circle.py
protograf/shapes_hexagon.py
protograf/shapes_rectangle.py
protograf/shapes_utils.py
protograf/utils/__init__.py
protograf/utils/colrs.py
protograf/utils/constants.py
protograf/utils/docstrings.py
protograf/utils/fonts.py
protograf/utils/geoms.py
protograf/utils/imaging.py
protograf/utils/lazy.py
protograf/utils/loadr.py
protograf/utils/messaging.py
protograf/utils/structures.py
protograf/utils/support.py
protograf/utils/tools.py
protograf-0.4.0.dist-info/METADATA
protograf-0.4.0.dist-info/WHEEL
protograf-0.4.0.dist-info/licenses/LICENSE
protograf-0.4.0.dist-info/RECORD
