Metadata-Version: 2.4
Name: protograf
Version: 0.4.0
Summary: Python utility for designing and creating simple, regular, graphic outputs as PDF/PNG files
License-Expression: GPL-3.0-or-later
License-File: LICENSE
Keywords: python,graphics,boardgames,cards,counters,tiles
Author: Derek Hohls
Author-email: gamesbook@gmail.com
Maintainer: Rory Meyer
Maintainer-email: rory@oceanmaps.xyz
Requires-Python: >=3.11,<4
Classifier: Programming Language :: Python :: 3.13
Classifier: Development Status :: 3 - Alpha
Classifier: Natural Language :: English
Classifier: Environment :: Console
Classifier: Intended Audience :: End Users/Desktop
Classifier: Operating System :: OS Independent
Classifier: Topic :: Software Development :: Libraries :: Python Modules
Classifier: Topic :: Games/Entertainment :: Board Games
Classifier: Topic :: Multimedia :: Graphics :: Presentation
Requires-Dist: bgg-api (>=1.1.14,<2.0.0)
Requires-Dist: black (>=25.1.0,<26.0.0)
Requires-Dist: cairosvg (>=2.7.1)
Requires-Dist: findsystemfontsfilename (>=0.3.2,<0.4.0)
Requires-Dist: fonttools (>=4.61.1,<5.0.0)
Requires-Dist: imageio (>=2.36.1)
Requires-Dist: jinja2 (>=3.1.4)
Requires-Dist: openpyxl (>=3.1.5,<4.0.0)
Requires-Dist: pymupdf (>=1.26.7,<2.0.0)
Requires-Dist: rich (>=14.0.0,<15.0.0)
Requires-Dist: segno (>=1.6.1)
Requires-Dist: sphinx-copybutton (>=0.5.2,<0.6.0)
Requires-Dist: tqdm (>=4.67.1,<5.0.0)
Requires-Dist: url-normalize (>=2.2.1,<3.0.0)
Requires-Dist: wand (>=0.6.13,<0.7.0)
Requires-Dist: xlrd (>=2.0.2,<3.0.0)
Project-URL: Bug Tracker, https://github.com/gamesbook/protograf/issues
Project-URL: Documentation, https://protograf.readthedocs.io/en/latest/
Project-URL: Repository, https://github.com/gamesbook/protograf
